tempo_ql/SQL_prompt.txt
tempo_ql/__init__.py
tempo_ql/ai_assistant.py
tempo_ql/data_types.py
tempo_ql/evaluator.py
tempo_ql/numba_functions.py
tempo_ql/prompt.txt
tempo_ql/utils.py
tempo_ql/widget.py
tempo_ql/generic/__init__.py
tempo_ql/generic/dataset.py
tempo_ql/generic/formats.py
tempo_ql/generic/variable_store.py
tempo_ql/meds/__init__.py
tempo_ql/meds/dataset.py
tempo_ql/static/style.css
tempo_ql/static/widget-main.js
tempo_ql-0.1.3.dist-info/licenses/LICENSE
tempo_ql-0.1.3.dist-info/METADATA
tempo_ql-0.1.3.dist-info/WHEEL
tempo_ql-0.1.3.dist-info/top_level.txt
tempo_ql-0.1.3.dist-info/RECORD
