Metadata-Version: 2.4
Name: tempo-ql
Version: 0.1.3
Summary: Toolkit and interactive widget for querying time-series healthcare data
Author-email: Venkatesh Sivaraman <venkats@cmu.edu>
License: MIT License
Project-URL: Homepage, https://github.com/cmudig/tempo-ql
Keywords: AI,machine learning,healthcare,EHR,OMOP,MEDS,data science
Classifier: Programming Language :: Python :: 3
Classifier: License :: OSI Approved :: MIT License
Requires-Python: >=3.10
License-File: LICENSE
Requires-Dist: numba>=0.59.0
Requires-Dist: numpy>=1.26.0
Requires-Dist: pandas>=2.0.0
Requires-Dist: scikit-learn>=1.3.2
Requires-Dist: tqdm>=4.66.1
Requires-Dist: lark>=1.1.8
Requires-Dist: pyarrow>=13.0.0
Requires-Dist: ipywidgets
Requires-Dist: anywidget
Requires-Dist: scipy>=1.11.3
Requires-Dist: sqlalchemy>=2.0.31
Requires-Dist: duckdb-engine
Requires-Dist: google-genai
Dynamic: license-file
